django_network_conditions/__init__.py
django_network_conditions/middleware.py
django_network_conditions/models.py
django_network_conditions-1.1.1.dist-info/LICENSE
django_network_conditions-1.1.1.dist-info/METADATA
django_network_conditions-1.1.1.dist-info/WHEEL
django_network_conditions-1.1.1.dist-info/top_level.txt
django_network_conditions-1.1.1.dist-info/RECORD
