Metadata-Version: 2.1
Name: django-network-conditions
Version: 1.1.1
Summary: Delay the response to simulate the real network conditions
Home-page: http://pypi.python.org/pypi/django-network-conditions
License: LICENSE
Platform: UNKNOWN
Requires-Dist: scipy
